chrysalio/__init__.py
chrysalio/initialize.py
chrysalio/menu.py
chrysalio/modes.py
chrysalio/relaxng.py
chrysalio/routes.py
chrysalio/security.py
chrysalio/subscribers.py
chrysalio/Locale/chrysalio.pot
chrysalio/Locale/fr/LC_MESSAGES/chrysalio.mo
chrysalio/Locale/fr/LC_MESSAGES/chrysalio.po
chrysalio/RelaxNG/chrysalio.rnc
chrysalio/RelaxNG/chrysalio.rng
chrysalio/Static/favicon.ico
chrysalio/Static/robots.txt
chrysalio/Static/Css/chrysalio.css
chrysalio/Static/Css/chrysalio.css.map
chrysalio/Static/Css/jquery-ui.css
chrysalio/Static/Custom/banner.png
chrysalio/Static/Custom/chrysalio_logo.png
chrysalio/Static/Custom/login_header.jpg
chrysalio/Static/Custom/login_logo.png
chrysalio/Static/Custom/menu_document.png
chrysalio/Static/Custom/menu_test1.png
chrysalio/Static/Custom/menu_test2.png
chrysalio/Static/Custom/menu_test3.png
chrysalio/Static/Images/action_cancel.png
chrysalio/Static/Images/action_configure.png
chrysalio/Static/Images/action_copy.png
chrysalio/Static/Images/action_cut.png
chrysalio/Static/Images/action_delete.png
chrysalio/Static/Images/action_delete_one.png
chrysalio/Static/Images/action_edit.png
chrysalio/Static/Images/action_edit_one.png
chrysalio/Static/Images/action_email.png
chrysalio/Static/Images/action_email_one.png
chrysalio/Static/Images/action_export.png
chrysalio/Static/Images/action_export_one.png
chrysalio/Static/Images/action_info.png
chrysalio/Static/Images/action_paste.png
chrysalio/Static/Images/action_start.png
chrysalio/Static/Images/action_start_one.png
chrysalio/Static/Images/action_stop.png
chrysalio/Static/Images/action_stop_one.png
chrysalio/Static/Images/checked.svg
chrysalio/Static/Images/close.png
chrysalio/Static/Images/dropdown.png
chrysalio/Static/Images/filter_toggle_minus.png
chrysalio/Static/Images/filter_toggle_plus.png
chrysalio/Static/Images/flash_alert.png
chrysalio/Static/Images/flash_info.png
chrysalio/Static/Images/group_picture.svg
chrysalio/Static/Images/help.png
chrysalio/Static/Images/job.png
Chrysalio-1.0.dist-info/METADATA
Chrysalio-1.0.dist-info/WHEEL
Chrysalio-1.0.dist-info/entry_points.txt
Chrysalio-1.0.dist-info/top_level.txt
Chrysalio-1.0.dist-info/RECORD
